CV_skeleton_provider/SPimage.py
CV_skeleton_provider/SPvideo.py
CV_skeleton_provider/SkeletonProvider.py
CV_skeleton_provider/__init__.py
CV_skeleton_provider/test.py
CV_skeleton_provider/utils_formatter.py
CV_skeleton_provider/utils_preprocessor.py
CV_skeleton_provider-1.0.1.dist-info/LICENSE
CV_skeleton_provider-1.0.1.dist-info/METADATA
CV_skeleton_provider-1.0.1.dist-info/WHEEL
CV_skeleton_provider-1.0.1.dist-info/top_level.txt
CV_skeleton_provider-1.0.1.dist-info/RECORD
