Metadata-Version: 2.1
Name: CV-skeleton-provider
Version: 1.0.1
Summary: provide skeleton of a person
Home-page: https://github.com/LiiNen/CV_skeleton_provider
Author: LiiNen
Author-email: kjeonghoon065@gmail.com
License: UNKNOWN
Keywords: Skeleton Provider
Platform: UNKNOWN
Classifier: Programming Language :: Python :: 3.5
Classifier: Programming Language :: Python :: 3.6
Classifier: Programming Language :: Python :: 3.7
Classifier: Programming Language :: Python :: 3.8
Classifier: Programming Language :: Python :: 3.9
Requires-Python: >=3
Requires-Dist: numpy
Requires-Dist: opencv-python
